src/__init__.py
src/__main__.py
src/cli.py
src/mapper.py
src/script.py
tests/test_main.py
venv/bin/activate_this.py
venv/bin/rst2html.py
venv/bin/rst2html4.py
venv/bin/rst2html5.py
venv/bin/rst2latex.py
venv/bin/rst2man.py
venv/bin/rst2odt.py
venv/bin/rst2odt_prepstyles.py
venv/bin/rst2pseudoxml.py
venv/bin/rst2s5.py
venv/bin/rst2xetex.py
venv/bin/rst2xml.py
venv/bin/rstpep2html.py
gwf_wrangler-0.0.7.dist-info/LICENSE
gwf_wrangler-0.0.7.dist-info/METADATA
gwf_wrangler-0.0.7.dist-info/WHEEL
gwf_wrangler-0.0.7.dist-info/entry_points.txt
gwf_wrangler-0.0.7.dist-info/top_level.txt
gwf_wrangler-0.0.7.dist-info/RECORD
