Metadata-Version: 2.1
Name: gwf-wrangler
Version: 0.0.7
Summary: A python package to convert yaml files to lua scripts for the Global Workflow Project.
Author-email: Ryan Long <ryan.long@noaa.gov>
License: Copyright 2023 NOAA
Project-URL: Homepage, https://github.com/pypa/gwf-wrangler
Project-URL: Bug Tracker, https://github.com/pypa/gwf-wrangler/issues
Keywords: globalworkflow,global workflow,esmf
Classifier: Programming Language :: Python :: 3
Classifier: License :: OSI Approved :: MIT License
Classifier: Operating System :: OS Independent
Requires-Python: >=3.7
License-File: LICENSE
Requires-Dist: PyYAML
Provides-Extra: dev
Requires-Dist: black ; extra == 'dev'
Requires-Dist: bumpver ; extra == 'dev'
Requires-Dist: isort ; extra == 'dev'
Requires-Dist: pip-tools ; extra == 'dev'
Requires-Dist: pytest ; extra == 'dev'
Requires-Dist: twine ; extra == 'dev'
Requires-Dist: build ; extra == 'dev'
